{
  "version": 1,
  "updatedAt": "2026-01-09T19:15:28Z",
  "slug": "billy-tuten",
  "roundCount": 4,
  "rounds": [
    {
      "id": "86CCAAF1-5BFB-5FC7-B5B9-5F8A6C0B5756",
      "date": "2001-09-28T00:00:00Z",
      "tournament": "Texas Open at LaCantera",
      "course": "LaCantera GC - San Antonio, TX",
      "roundNumber": 2,
      "score": 71,
      "par": 72,
      "notes": "Source: PGA Tour Results TSV",
      "differential": 0.34,
      "fieldAverage": 70.66,
      "fieldSize": 151,
      "slope": 113,
      "courseRating": 70.66,
      "source": "Field Avg"
    },
    {
      "id": "64A8AF78-F8F9-5591-BBED-CAF7BD4AC1E1",
      "date": "2001-09-27T00:00:00Z",
      "tournament": "Texas Open at LaCantera",
      "course": "LaCantera GC - San Antonio, TX",
      "roundNumber": 1,
      "score": 72,
      "par": 72,
      "notes": "Source: PGA Tour Results TSV",
      "differential": 1.59,
      "fieldAverage": 70.41,
      "fieldSize": 152,
      "slope": 113,
      "courseRating": 70.41,
      "source": "Field Avg"
    },
    {
      "id": "F9205E1A-3A34-5C0F-A0C8-A1C99B359BDF",
      "date": "2001-05-11T00:00:00Z",
      "tournament": "Verizon Byron Nelson Classic",
      "course": "TPC Four Seasons Resort - Irving, TX",
      "roundNumber": 2,
      "score": 69,
      "par": 72,
      "notes": "Source: PGA Tour Results TSV",
      "differential": -0.23,
      "fieldAverage": 69.23,
      "fieldSize": 154,
      "slope": 113,
      "courseRating": 69.23,
      "source": "Field Avg"
    },
    {
      "id": "83A832B7-A95C-569B-A8A0-0210334BEE65",
      "date": "2001-05-10T00:00:00Z",
      "tournament": "Verizon Byron Nelson Classic",
      "course": "TPC Four Seasons Resort - Irving, TX",
      "roundNumber": 1,
      "score": 74,
      "par": 72,
      "notes": "Source: PGA Tour Results TSV",
      "differential": 3.95,
      "fieldAverage": 70.05,
      "fieldSize": 154,
      "slope": 113,
      "courseRating": 70.05,
      "source": "Field Avg"
    }
  ]
}