{
  "version": 1,
  "updatedAt": "2026-01-09T19:15:28Z",
  "slug": "frank-dully",
  "roundCount": 2,
  "rounds": [
    {
      "id": "8C39C273-08B4-55E4-8CFD-9FF18C72B283",
      "date": "2006-09-02T00:00:00Z",
      "tournament": "Deutsche Bank Championship",
      "course": "TPC Boston - Norton, MA",
      "roundNumber": 2,
      "score": 77,
      "par": 72,
      "notes": "Source: PGA Tour Results TSV"
    },
    {
      "id": "A874309B-2BFC-5F42-B773-8D4B6E65CBD2",
      "date": "2006-09-01T00:00:00Z",
      "tournament": "Deutsche Bank Championship",
      "course": "TPC Boston - Norton, MA",
      "roundNumber": 1,
      "score": 75,
      "par": 72,
      "notes": "Source: PGA Tour Results TSV"
    }
  ]
}