{
  "version": 1,
  "updatedAt": "2026-01-09T19:15:28Z",
  "slug": "frazer-jones-a",
  "roundCount": 2,
  "rounds": [
    {
      "id": "99B3C46D-E585-56BD-9D3D-BD231714CF6C",
      "date": "2025-07-18T00:00:00Z",
      "tournament": "The Open",
      "course": "Royal Portrush Golf Club - Portrush, Northern Ireland",
      "roundNumber": 2,
      "score": 73,
      "par": 72,
      "notes": "Source: PGA Tour Results TSV",
      "differential": -3.0,
      "fieldAverage": 71.41,
      "fieldSize": 156,
      "slope": 143,
      "courseRating": 76.8,
      "source": "USGA"
    },
    {
      "id": "703A0C48-883D-5CB6-B943-67972917AC9F",
      "date": "2025-07-17T00:00:00Z",
      "tournament": "The Open",
      "course": "Royal Portrush Golf Club - Portrush, Northern Ireland",
      "roundNumber": 1,
      "score": 77,
      "par": 72,
      "notes": "Source: PGA Tour Results TSV",
      "differential": 0.16,
      "fieldAverage": 73.04,
      "fieldSize": 156,
      "slope": 143,
      "courseRating": 76.8,
      "source": "USGA"
    }
  ]
}