{
  "version": 1,
  "updatedAt": "2026-01-09T19:15:28Z",
  "slug": "ockie-strydom",
  "roundCount": 10,
  "rounds": [
    {
      "id": "4D7B26FB-D935-5200-81C0-62324B010012",
      "date": "2025-07-11T00:00:00Z",
      "tournament": "Genesis Scottish Open",
      "course": "The Renaissance Club - North Berwick, Scotland",
      "roundNumber": 2,
      "score": 73,
      "par": 72,
      "notes": "Source: PGA Tour Results TSV"
    },
    {
      "id": "8B2743D4-9EC7-55B2-90BE-F7D82FC9C63A",
      "date": "2025-07-10T00:00:00Z",
      "tournament": "Genesis Scottish Open",
      "course": "The Renaissance Club - North Berwick, Scotland",
      "roundNumber": 1,
      "score": 74,
      "par": 72,
      "notes": "Source: PGA Tour Results TSV"
    },
    {
      "id": "4570369F-1A8B-51CD-9254-45B3DE3A1709",
      "date": "2024-07-12T00:00:00Z",
      "tournament": "Genesis Scottish Open",
      "course": "The Renaissance Club - North Berwick, Scotland",
      "roundNumber": 2,
      "score": 68,
      "par": 72,
      "notes": "Source: PGA Tour Results TSV"
    },
    {
      "id": "10F5F591-B5C2-5395-8351-B8B28572102F",
      "date": "2024-07-11T00:00:00Z",
      "tournament": "Genesis Scottish Open",
      "course": "The Renaissance Club - North Berwick, Scotland",
      "roundNumber": 1,
      "score": 73,
      "par": 72,
      "notes": "Source: PGA Tour Results TSV"
    },
    {
      "id": "A1C7A0BB-B2B3-566E-A244-48BE388D12D8",
      "date": "2023-07-21T00:00:00Z",
      "tournament": "The Open",
      "course": "Royal Liverpool GC - Hoylake",
      "roundNumber": 2,
      "score": 77,
      "par": 72,
      "notes": "Source: PGA Tour Results TSV"
    },
    {
      "id": "28938616-B6CD-573B-87B9-ED9931A4097D",
      "date": "2023-07-20T00:00:00Z",
      "tournament": "The Open",
      "course": "Royal Liverpool GC - Hoylake",
      "roundNumber": 1,
      "score": 72,
      "par": 72,
      "notes": "Source: PGA Tour Results TSV"
    },
    {
      "id": "7187D641-E786-51FA-99BB-4318133D24EA",
      "date": "2023-07-14T00:00:00Z",
      "tournament": "Genesis Scottish Open",
      "course": "The Renaissance Club - North Berwick, Scotland",
      "roundNumber": 2,
      "score": 74,
      "par": 72,
      "notes": "Source: PGA Tour Results TSV"
    },
    {
      "id": "ECA29DA8-ED5B-5150-A082-56D0932E0C5D",
      "date": "2023-07-13T00:00:00Z",
      "tournament": "Genesis Scottish Open",
      "course": "The Renaissance Club - North Berwick, Scotland",
      "roundNumber": 1,
      "score": 69,
      "par": 72,
      "notes": "Source: PGA Tour Results TSV"
    },
    {
      "id": "B0C8BE48-D56A-52AE-BFA8-6DE0BD30FECE",
      "date": "2023-05-19T00:00:00Z",
      "tournament": "PGA Championship",
      "course": "Oak Hill Country Club - Rochester, NY",
      "roundNumber": 2,
      "score": 76,
      "par": 72,
      "notes": "Source: PGA Tour Results TSV"
    },
    {
      "id": "1BFA9E39-8B0B-5A68-9F19-69E90E39DE87",
      "date": "2023-05-18T00:00:00Z",
      "tournament": "PGA Championship",
      "course": "Oak Hill Country Club - Rochester, NY",
      "roundNumber": 1,
      "score": 77,
      "par": 72,
      "notes": "Source: PGA Tour Results TSV"
    }
  ]
}